limitless/__init__.py
limitless/main.py
limitless-0.0.2.dist-info/DESCRIPTION.rst
limitless-0.0.2.dist-info/METADATA
limitless-0.0.2.dist-info/RECORD
limitless-0.0.2.dist-info/WHEEL
limitless-0.0.2.dist-info/entry_points.txt
limitless-0.0.2.dist-info/metadata.json
limitless-0.0.2.dist-info/top_level.txt
